[
  {
    "algorithm": "LocalOutlierFactor",
    "params": {
      "n_neighbors": 5,
      "contamination": 0.05,
      "novelty": true
    },
    "accuracy": 0.9702703963428856,
    "balanced_accuracy": 0.9603160420202724,
    "precision": 0.9987668115526591,
    "recall": 0.9707581124801701,
    "f1_score": 0.9845633055563565,
    "roc_auc": 0.032781043615873286,
    "training_time": 138.00231766700745,
    "prediction_time": 125.80636763572693,
    "total_time": 138.0043294429779,
    "memory_usage_mb": 59.89453125,
    "confusion_matrix": {
      "tn": 19973,
      "fp": 1054,
      "fn": 25714,
      "tp": 853641
    },
    "success": true,
    "error": null,
    "run_id": 0,
    "param_id": 0,
    "config_index": 0,
    "run_index": 0,
    "test_mode": false
  },
  {
    "algorithm": "LocalOutlierFactor",
    "params": {
      "n_neighbors": 5,
      "contamination": 0.05,
      "novelty": true
    },
    "accuracy": 0.9702703963428856,
    "balanced_accuracy": 0.9603160420202724,
    "precision": 0.9987668115526591,
    "recall": 0.9707581124801701,
    "f1_score": 0.9845633055563565,
    "roc_auc": 0.032781043615873286,
    "training_time": 139.5542027950287,
    "prediction_time": 126.83775520324707,
    "total_time": 139.55647325515747,
    "memory_usage_mb": 27.83984375,
    "confusion_matrix": {
      "tn": 19973,
      "fp": 1054,
      "fn": 25714,
      "tp": 853641
    },
    "success": true,
    "error": null,
    "run_id": 1,
    "param_id": 0,
    "config_index": 0,
    "run_index": 1,
    "test_mode": false
  },
  {
    "algorithm": "LocalOutlierFactor",
    "params": {
      "n_neighbors": 5,
      "contamination": 0.05,
      "novelty": true
    },
    "accuracy": 0.9702703963428856,
    "balanced_accuracy": 0.9603160420202724,
    "precision": 0.9987668115526591,
    "recall": 0.9707581124801701,
    "f1_score": 0.9845633055563565,
    "roc_auc": 0.032781043615873286,
    "training_time": 139.11075925827026,
    "prediction_time": 126.43029928207397,
    "total_time": 139.11596298217773,
    "memory_usage_mb": 56.96875,
    "confusion_matrix": {
      "tn": 19973,
      "fp": 1054,
      "fn": 25714,
      "tp": 853641
    },
    "success": true,
    "error": null,
    "run_id": 2,
    "param_id": 0,
    "config_index": 0,
    "run_index": 2,
    "test_mode": false
  },
  {
    "algorithm": "LocalOutlierFactor",
    "params": {
      "n_neighbors": 5,
      "contamination": 0.1,
      "novelty": true
    },
    "accuracy": 0.9783669598015065,
    "balanced_accuracy": 0.9384887414116835,
    "precision": 0.9974856026743097,
    "recall": 0.9803208033160669,
    "f1_score": 0.988828718875783,
    "roc_auc": 0.03278104526539595,
    "training_time": 138.98997712135315,
    "prediction_time": 126.42697739601135,
    "total_time": 138.99530458450317,
    "memory_usage_mb": 56.65234375,
    "confusion_matrix": {
      "tn": 18854,
      "fp": 2173,
      "fn": 17305,
      "tp": 862050
    },
    "success": true,
    "error": null,
    "run_id": 0,
    "param_id": 1,
    "config_index": 1,
    "run_index": 0,
    "test_mode": false
  },
  {
    "algorithm": "LocalOutlierFactor",
    "params": {
      "n_neighbors": 5,
      "contamination": 0.1,
      "novelty": true
    },
    "accuracy": 0.9783669598015065,
    "balanced_accuracy": 0.9384887414116835,
    "precision": 0.9974856026743097,
    "recall": 0.9803208033160669,
    "f1_score": 0.988828718875783,
    "roc_auc": 0.03278104526539595,
    "training_time": 138.31779789924622,
    "prediction_time": 126.21678686141968,
    "total_time": 138.32005333900452,
    "memory_usage_mb": 56.85546875,
    "confusion_matrix": {
      "tn": 18854,
      "fp": 2173,
      "fn": 17305,
      "tp": 862050
    },
    "success": true,
    "error": null,
    "run_id": 1,
    "param_id": 1,
    "config_index": 1,
    "run_index": 1,
    "test_mode": false
  },
  {
    "algorithm": "LocalOutlierFactor",
    "params": {
      "n_neighbors": 5,
      "contamination": 0.1,
      "novelty": true
    },
    "accuracy": 0.9783669598015065,
    "balanced_accuracy": 0.9384887414116835,
    "precision": 0.9974856026743097,
    "recall": 0.9803208033160669,
    "f1_score": 0.988828718875783,
    "roc_auc": 0.03278104526539595,
    "training_time": 138.93741297721863,
    "prediction_time": 126.59584832191467,
    "total_time": 138.9397566318512,
    "memory_usage_mb": 56.69921875,
    "confusion_matrix": {
      "tn": 18854,
      "fp": 2173,
      "fn": 17305,
      "tp": 862050
    },
    "success": true,
    "error": null,
    "run_id": 2,
    "param_id": 1,
    "config_index": 1,
    "run_index": 2,
    "test_mode": false
  },
  {
    "algorithm": "LocalOutlierFactor",
    "params": {
      "n_neighbors": 10,
      "contamination": 0.1,
      "novelty": true
    },
    "accuracy": 0.9792077140591438,
    "balanced_accuracy": 0.940938471182919,
    "precision": 0.9975878983263299,
    "recall": 0.9810827254066902,
    "f1_score": 0.9892664725332122,
    "roc_auc": 0.030095049008639352,
    "training_time": 139.58491349220276,
    "prediction_time": 127.0014922618866,
    "total_time": 139.5872688293457,
    "memory_usage_mb": 55.9296875,
    "confusion_matrix": {
      "tn": 18941,
      "fp": 2086,
      "fn": 16635,
      "tp": 862720
    },
    "success": true,
    "error": null,
    "run_id": 0,
    "param_id": 2,
    "config_index": 2,
    "run_index": 0,
    "test_mode": false
  },
  {
    "algorithm": "LocalOutlierFactor",
    "params": {
      "n_neighbors": 10,
      "contamination": 0.1,
      "novelty": true
    },
    "accuracy": 0.9792077140591438,
    "balanced_accuracy": 0.940938471182919,
    "precision": 0.9975878983263299,
    "recall": 0.9810827254066902,
    "f1_score": 0.9892664725332122,
    "roc_auc": 0.030095049008639352,
    "training_time": 138.38685631752014,
    "prediction_time": 126.30172801017761,
    "total_time": 138.38921737670898,
    "memory_usage_mb": 55.9296875,
    "confusion_matrix": {
      "tn": 18941,
      "fp": 2086,
      "fn": 16635,
      "tp": 862720
    },
    "success": true,
    "error": null,
    "run_id": 1,
    "param_id": 2,
    "config_index": 2,
    "run_index": 1,
    "test_mode": false
  },
  {
    "algorithm": "LocalOutlierFactor",
    "params": {
      "n_neighbors": 10,
      "contamination": 0.1,
      "novelty": true
    },
    "accuracy": 0.9792077140591438,
    "balanced_accuracy": 0.940938471182919,
    "precision": 0.9975878983263299,
    "recall": 0.9810827254066902,
    "f1_score": 0.9892664725332122,
    "roc_auc": 0.030095049008639352,
    "training_time": 138.25636959075928,
    "prediction_time": 126.12917137145996,
    "total_time": 138.25875782966614,
    "memory_usage_mb": 55.9296875,
    "confusion_matrix": {
      "tn": 18941,
      "fp": 2086,
      "fn": 16635,
      "tp": 862720
    },
    "success": true,
    "error": null,
    "run_id": 2,
    "param_id": 2,
    "config_index": 2,
    "run_index": 2,
    "test_mode": false
  },
  {
    "algorithm": "LocalOutlierFactor",
    "params": {
      "n_neighbors": 15,
      "contamination": 0.1,
      "novelty": true
    },
    "accuracy": 0.9799796086549931,
    "balanced_accuracy": 0.9398017639409666,
    "precision": 0.9975139579937456,
    "recall": 0.9819481324379801,
    "f1_score": 0.9896698430017857,
    "roc_auc": 0.02728653156250196,
    "training_time": 140.4832887649536,
    "prediction_time": 127.9641923904419,
    "total_time": 140.48542380332947,
    "memory_usage_mb": 68.765625,
    "confusion_matrix": {
      "tn": 18875,
      "fp": 2152,
      "fn": 15874,
      "tp": 863481
    },
    "success": true,
    "error": null,
    "run_id": 0,
    "param_id": 3,
    "config_index": 3,
    "run_index": 0,
    "test_mode": false
  },
  {
    "algorithm": "LocalOutlierFactor",
    "params": {
      "n_neighbors": 15,
      "contamination": 0.1,
      "novelty": true
    },
    "accuracy": 0.9799796086549931,
    "balanced_accuracy": 0.9398017639409666,
    "precision": 0.9975139579937456,
    "recall": 0.9819481324379801,
    "f1_score": 0.9896698430017857,
    "roc_auc": 0.02728653156250196,
    "training_time": 139.1220362186432,
    "prediction_time": 126.91896057128906,
    "total_time": 139.12434935569763,
    "memory_usage_mb": 68.765625,
    "confusion_matrix": {
      "tn": 18875,
      "fp": 2152,
      "fn": 15874,
      "tp": 863481
    },
    "success": true,
    "error": null,
    "run_id": 1,
    "param_id": 3,
    "config_index": 3,
    "run_index": 1,
    "test_mode": false
  },
  {
    "algorithm": "LocalOutlierFactor",
    "params": {
      "n_neighbors": 15,
      "contamination": 0.1,
      "novelty": true
    },
    "accuracy": 0.9799796086549931,
    "balanced_accuracy": 0.9398017639409666,
    "precision": 0.9975139579937456,
    "recall": 0.9819481324379801,
    "f1_score": 0.9896698430017857,
    "roc_auc": 0.02728653156250196,
    "training_time": 139.77561712265015,
    "prediction_time": 127.30601286888123,
    "total_time": 139.77779293060303,
    "memory_usage_mb": 68.7109375,
    "confusion_matrix": {
      "tn": 18875,
      "fp": 2152,
      "fn": 15874,
      "tp": 863481
    },
    "success": true,
    "error": null,
    "run_id": 2,
    "param_id": 3,
    "config_index": 3,
    "run_index": 2,
    "test_mode": false
  },
  {
    "algorithm": "LocalOutlierFactor",
    "params": {
      "n_neighbors": 20,
      "contamination": 0.1,
      "novelty": true
    },
    "accuracy": 0.9805049412360531,
    "balanced_accuracy": 0.9414633322048408,
    "precision": 0.9975842565584201,
    "recall": 0.9824177948610061,
    "f1_score": 0.9899429395172634,
    "roc_auc": 0.02574153111733771,
    "training_time": 140.6618275642395,
    "prediction_time": 128.07463026046753,
    "total_time": 140.66869711875916,
    "memory_usage_mb": 81.625,
    "confusion_matrix": {
      "tn": 18935,
      "fp": 2092,
      "fn": 15461,
      "tp": 863894
    },
    "success": true,
    "error": null,
    "run_id": 0,
    "param_id": 4,
    "config_index": 4,
    "run_index": 0,
    "test_mode": false
  },
  {
    "algorithm": "LocalOutlierFactor",
    "params": {
      "n_neighbors": 20,
      "contamination": 0.1,
      "novelty": true
    },
    "accuracy": 0.9805049412360531,
    "balanced_accuracy": 0.9414633322048408,
    "precision": 0.9975842565584201,
    "recall": 0.9824177948610061,
    "f1_score": 0.9899429395172634,
    "roc_auc": 0.02574153111733771,
    "training_time": 140.87763047218323,
    "prediction_time": 128.54985308647156,
    "total_time": 140.8801827430725,
    "memory_usage_mb": 81.546875,
    "confusion_matrix": {
      "tn": 18935,
      "fp": 2092,
      "fn": 15461,
      "tp": 863894
    },
    "success": true,
    "error": null,
    "run_id": 1,
    "param_id": 4,
    "config_index": 4,
    "run_index": 1,
    "test_mode": false
  },
  {
    "algorithm": "LocalOutlierFactor",
    "params": {
      "n_neighbors": 20,
      "contamination": 0.1,
      "novelty": true
    },
    "accuracy": 0.9805049412360531,
    "balanced_accuracy": 0.9414633322048408,
    "precision": 0.9975842565584201,
    "recall": 0.9824177948610061,
    "f1_score": 0.9899429395172634,
    "roc_auc": 0.02574153111733771,
    "training_time": 152.38775157928467,
    "prediction_time": 139.90702652931213,
    "total_time": 152.39022636413574,
    "memory_usage_mb": 81.54296875,
    "confusion_matrix": {
      "tn": 18935,
      "fp": 2092,
      "fn": 15461,
      "tp": 863894
    },
    "success": true,
    "error": null,
    "run_id": 2,
    "param_id": 4,
    "config_index": 4,
    "run_index": 2,
    "test_mode": false
  },
  {
    "algorithm": "LocalOutlierFactor",
    "params": {
      "n_neighbors": 20,
      "contamination": 0.15,
      "novelty": true
    },
    "accuracy": 0.981550053199642,
    "balanced_accuracy": 0.9170704650963848,
    "precision": 0.9963570462848431,
    "recall": 0.9847092471186267,
    "f1_score": 0.9904989047316736,
    "roc_auc": 0.02574153111733771,
    "training_time": 158.18062019348145,
    "prediction_time": 144.41758251190186,
    "total_time": 158.183119058609,
    "memory_usage_mb": 81.44140625,
    "confusion_matrix": {
      "tn": 17861,
      "fp": 3166,
      "fn": 13446,
      "tp": 865909
    },
    "success": true,
    "error": null,
    "run_id": 0,
    "param_id": 5,
    "config_index": 5,
    "run_index": 0,
    "test_mode": false
  },
  {
    "algorithm": "LocalOutlierFactor",
    "params": {
      "n_neighbors": 20,
      "contamination": 0.15,
      "novelty": true
    },
    "accuracy": 0.981550053199642,
    "balanced_accuracy": 0.9170704650963848,
    "precision": 0.9963570462848431,
    "recall": 0.9847092471186267,
    "f1_score": 0.9904989047316736,
    "roc_auc": 0.02574153111733771,
    "training_time": 156.48118138313293,
    "prediction_time": 142.51926445960999,
    "total_time": 156.48370814323425,
    "memory_usage_mb": 81.5546875,
    "confusion_matrix": {
      "tn": 17861,
      "fp": 3166,
      "fn": 13446,
      "tp": 865909
    },
    "success": true,
    "error": null,
    "run_id": 1,
    "param_id": 5,
    "config_index": 5,
    "run_index": 1,
    "test_mode": false
  },
  {
    "algorithm": "LocalOutlierFactor",
    "params": {
      "n_neighbors": 20,
      "contamination": 0.15,
      "novelty": true
    },
    "accuracy": 0.981550053199642,
    "balanced_accuracy": 0.9170704650963848,
    "precision": 0.9963570462848431,
    "recall": 0.9847092471186267,
    "f1_score": 0.9904989047316736,
    "roc_auc": 0.02574153111733771,
    "training_time": 156.619975566864,
    "prediction_time": 142.63813853263855,
    "total_time": 156.62263250350952,
    "memory_usage_mb": 81.55078125,
    "confusion_matrix": {
      "tn": 17861,
      "fp": 3166,
      "fn": 13446,
      "tp": 865909
    },
    "success": true,
    "error": null,
    "run_id": 2,
    "param_id": 5,
    "config_index": 5,
    "run_index": 2,
    "test_mode": false
  },
  {
    "algorithm": "LocalOutlierFactor",
    "params": {
      "n_neighbors": 30,
      "contamination": 0.15,
      "novelty": true
    },
    "accuracy": 0.981593368148186,
    "balanced_accuracy": 0.9187869961585378,
    "precision": 0.9964406054077941,
    "recall": 0.9846705824155204,
    "f1_score": 0.9905206303411899,
    "roc_auc": 0.026213898000376615,
    "training_time": 159.51104760169983,
    "prediction_time": 145.44557523727417,
    "total_time": 159.513445854187,
    "memory_usage_mb": 107.26953125,
    "confusion_matrix": {
      "tn": 17934,
      "fp": 3093,
      "fn": 13480,
      "tp": 865875
    },
    "success": true,
    "error": null,
    "run_id": 0,
    "param_id": 6,
    "config_index": 6,
    "run_index": 0,
    "test_mode": false
  },
  {
    "algorithm": "LocalOutlierFactor",
    "params": {
      "n_neighbors": 30,
      "contamination": 0.15,
      "novelty": true
    },
    "accuracy": 0.981593368148186,
    "balanced_accuracy": 0.9187869961585378,
    "precision": 0.9964406054077941,
    "recall": 0.9846705824155204,
    "f1_score": 0.9905206303411899,
    "roc_auc": 0.026213898000376615,
    "training_time": 157.9583010673523,
    "prediction_time": 143.5243752002716,
    "total_time": 157.96077418327332,
    "memory_usage_mb": 107.31640625,
    "confusion_matrix": {
      "tn": 17934,
      "fp": 3093,
      "fn": 13480,
      "tp": 865875
    },
    "success": true,
    "error": null,
    "run_id": 1,
    "param_id": 6,
    "config_index": 6,
    "run_index": 1,
    "test_mode": false
  },
  {
    "algorithm": "LocalOutlierFactor",
    "params": {
      "n_neighbors": 30,
      "contamination": 0.15,
      "novelty": true
    },
    "accuracy": 0.981593368148186,
    "balanced_accuracy": 0.9187869961585378,
    "precision": 0.9964406054077941,
    "recall": 0.9846705824155204,
    "f1_score": 0.9905206303411899,
    "roc_auc": 0.026213898000376615,
    "training_time": 157.82484221458435,
    "prediction_time": 143.87227773666382,
    "total_time": 157.827330827713,
    "memory_usage_mb": 107.3359375,
    "confusion_matrix": {
      "tn": 17934,
      "fp": 3093,
      "fn": 13480,
      "tp": 865875
    },
    "success": true,
    "error": null,
    "run_id": 2,
    "param_id": 6,
    "config_index": 6,
    "run_index": 2,
    "test_mode": false
  },
  {
    "algorithm": "LocalOutlierFactor",
    "params": {
      "n_neighbors": 50,
      "contamination": 0.15,
      "novelty": true
    },
    "accuracy": 0.9817910620158999,
    "balanced_accuracy": 0.9192363619893681,
    "precision": 0.9964584704458324,
    "recall": 0.9848559455510004,
    "f1_score": 0.9906232359587319,
    "roc_auc": 0.029229530053180325,
    "training_time": 161.34349846839905,
    "prediction_time": 146.96539115905762,
    "total_time": 161.34651923179626,
    "memory_usage_mb": 74.5859375,
    "confusion_matrix": {
      "tn": 17949,
      "fp": 3078,
      "fn": 13317,
      "tp": 866038
    },
    "success": true,
    "error": null,
    "run_id": 0,
    "param_id": 7,
    "config_index": 7,
    "run_index": 0,
    "test_mode": false
  },
  {
    "algorithm": "LocalOutlierFactor",
    "params": {
      "n_neighbors": 50,
      "contamination": 0.15,
      "novelty": true
    },
    "accuracy": 0.9817910620158999,
    "balanced_accuracy": 0.9192363619893681,
    "precision": 0.9964584704458324,
    "recall": 0.9848559455510004,
    "f1_score": 0.9906232359587319,
    "roc_auc": 0.029229530053180325,
    "training_time": 159.87158298492432,
    "prediction_time": 145.5663025379181,
    "total_time": 159.87392020225525,
    "memory_usage_mb": 32.1953125,
    "confusion_matrix": {
      "tn": 17949,
      "fp": 3078,
      "fn": 13317,
      "tp": 866038
    },
    "success": true,
    "error": null,
    "run_id": 1,
    "param_id": 7,
    "config_index": 7,
    "run_index": 1,
    "test_mode": false
  },
  {
    "algorithm": "LocalOutlierFactor",
    "params": {
      "n_neighbors": 50,
      "contamination": 0.15,
      "novelty": true
    },
    "accuracy": 0.9817910620158999,
    "balanced_accuracy": 0.9192363619893681,
    "precision": 0.9964584704458324,
    "recall": 0.9848559455510004,
    "f1_score": 0.9906232359587319,
    "roc_auc": 0.029229530053180325,
    "training_time": 161.01990628242493,
    "prediction_time": 146.43164658546448,
    "total_time": 161.02253317832947,
    "memory_usage_mb": 32.02734375,
    "confusion_matrix": {
      "tn": 17949,
      "fp": 3078,
      "fn": 13317,
      "tp": 866038
    },
    "success": true,
    "error": null,
    "run_id": 2,
    "param_id": 7,
    "config_index": 7,
    "run_index": 2,
    "test_mode": false
  },
  {
    "algorithm": "LocalOutlierFactor",
    "params": {
      "n_neighbors": 50,
      "contamination": 0.2,
      "novelty": true
    },
    "accuracy": 0.9823752585013916,
    "balanced_accuracy": 0.8936094813234523,
    "precision": 0.9951885359844749,
    "recall": 0.9867243604687527,
    "f1_score": 0.9909383742064868,
    "roc_auc": 0.029229530053180325,
    "training_time": 161.16671419143677,
    "prediction_time": 146.8415277004242,
    "total_time": 161.168865442276,
    "memory_usage_mb": 32.12109375,
    "confusion_matrix": {
      "tn": 16832,
      "fp": 4195,
      "fn": 11674,
      "tp": 867681
    },
    "success": true,
    "error": null,
    "run_id": 0,
    "param_id": 8,
    "config_index": 8,
    "run_index": 0,
    "test_mode": false
  },
  {
    "algorithm": "LocalOutlierFactor",
    "params": {
      "n_neighbors": 50,
      "contamination": 0.2,
      "novelty": true
    },
    "accuracy": 0.9823752585013916,
    "balanced_accuracy": 0.8936094813234523,
    "precision": 0.9951885359844749,
    "recall": 0.9867243604687527,
    "f1_score": 0.9909383742064868,
    "roc_auc": 0.029229530053180325,
    "training_time": 159.89842629432678,
    "prediction_time": 145.3740656375885,
    "total_time": 159.9009428024292,
    "memory_usage_mb": 32.23828125,
    "confusion_matrix": {
      "tn": 16832,
      "fp": 4195,
      "fn": 11674,
      "tp": 867681
    },
    "success": true,
    "error": null,
    "run_id": 1,
    "param_id": 8,
    "config_index": 8,
    "run_index": 1,
    "test_mode": false
  },
  {
    "algorithm": "LocalOutlierFactor",
    "params": {
      "n_neighbors": 50,
      "contamination": 0.2,
      "novelty": true
    },
    "accuracy": 0.9823752585013916,
    "balanced_accuracy": 0.8936094813234523,
    "precision": 0.9951885359844749,
    "recall": 0.9867243604687527,
    "f1_score": 0.9909383742064868,
    "roc_auc": 0.029229530053180325,
    "training_time": 160.34860491752625,
    "prediction_time": 146.1396176815033,
    "total_time": 160.35103845596313,
    "memory_usage_mb": 32.23828125,
    "confusion_matrix": {
      "tn": 16832,
      "fp": 4195,
      "fn": 11674,
      "tp": 867681
    },
    "success": true,
    "error": null,
    "run_id": 2,
    "param_id": 8,
    "config_index": 8,
    "run_index": 2,
    "test_mode": false
  },
  {
    "algorithm": "LocalOutlierFactor",
    "params": {
      "n_neighbors": 100,
      "contamination": 0.2,
      "novelty": true
    },
    "accuracy": 0.9823708159425666,
    "balanced_accuracy": 0.8946748831348412,
    "precision": 0.9952407717543417,
    "recall": 0.9866675006112434,
    "f1_score": 0.9909355932009811,
    "roc_auc": 0.028783675623442515,
    "training_time": 168.0608582496643,
    "prediction_time": 153.44492483139038,
    "total_time": 168.06309461593628,
    "memory_usage_mb": 64.234375,
    "confusion_matrix": {
      "tn": 16878,
      "fp": 4149,
      "fn": 11724,
      "tp": 867631
    },
    "success": true,
    "error": null,
    "run_id": 0,
    "param_id": 9,
    "config_index": 9,
    "run_index": 0,
    "test_mode": false
  },
  {
    "algorithm": "LocalOutlierFactor",
    "params": {
      "n_neighbors": 100,
      "contamination": 0.2,
      "novelty": true
    },
    "accuracy": 0.9823708159425666,
    "balanced_accuracy": 0.8946748831348412,
    "precision": 0.9952407717543417,
    "recall": 0.9866675006112434,
    "f1_score": 0.9909355932009811,
    "roc_auc": 0.028783675623442515,
    "training_time": 172.0304090976715,
    "prediction_time": 156.7601833343506,
    "total_time": 172.03274655342102,
    "memory_usage_mb": 64.13671875,
    "confusion_matrix": {
      "tn": 16878,
      "fp": 4149,
      "fn": 11724,
      "tp": 867631
    },
    "success": true,
    "error": null,
    "run_id": 1,
    "param_id": 9,
    "config_index": 9,
    "run_index": 1,
    "test_mode": false
  },
  {
    "algorithm": "LocalOutlierFactor",
    "params": {
      "n_neighbors": 100,
      "contamination": 0.2,
      "novelty": true
    },
    "accuracy": 0.9823708159425666,
    "balanced_accuracy": 0.8946748831348412,
    "precision": 0.9952407717543417,
    "recall": 0.9866675006112434,
    "f1_score": 0.9909355932009811,
    "roc_auc": 0.028783675623442515,
    "training_time": 165.7188766002655,
    "prediction_time": 150.48203110694885,
    "total_time": 165.72114253044128,
    "memory_usage_mb": 64.22265625,
    "confusion_matrix": {
      "tn": 16878,
      "fp": 4149,
      "fn": 11724,
      "tp": 867631
    },
    "success": true,
    "error": null,
    "run_id": 2,
    "param_id": 9,
    "config_index": 9,
    "run_index": 2,
    "test_mode": false
  }
]